Workbook

Sheet Instruções
B1: SIPOC — Como usar esta planilha
B2: Modelo para mapear um processo em alto nível: Fornecedores, Entradas, Processo, Saídas e Clientes.
B4: Legenda: onde preencher
B5: Amarelo-claro | C5: Células de entrada. É aqui que você digita.
B6: Cinza | C6: Células calculadas ou fixas (rótulos, contagens, avisos). Não altere.
B7: Cinza em itálico | C7: Linha de exemplo (marcada com “Ex.”). Mostra o formato esperado e não entra nas contagens.
B8: Listas suspensas | C8: Colunas de status, impacto e elemento aceitam apenas as opções da lista.
B9: Comentários | C9: Células com triângulo vermelho no canto trazem uma dica de preenchimento. Passe o mouse sobre elas.
B11: As cinco colunas
B12: S | C12: Fornecedores: quem entrega as entradas. Pode ser uma pessoa, área, empresa ou sistema.
B13: I | C13: Entradas: materiais, informações ou serviços que o processo consome ou transforma.
B14: P | C14: Processo: as macroetapas, em ordem, escritas com verbo no infinitivo + objeto.
B15: O | C15: Saídas: produtos, serviços ou informações que o processo entrega.
B16: C | C16: Clientes: quem recebe cada saída. Pode ser interno ou externo.
B18: Ordem recomendada de preenchimento (aba SIPOC)
B19: Passo 1 | C19: Preencha o cabeçalho: nome do processo, dono, objetivo, início (gatilho) e fim (entrega final).
B20: Passo 2 | C20: Coluna P: liste de 4 a 7 macroetapas, na ordem em que acontecem.
B21: Passo 3 | C21: Coluna O: liste o que o processo entrega.
B22: Passo 4 | C22: Coluna C: na mesma linha de cada saída, escreva quem a recebe.
B23: Passo 5 | C23: Coluna I: liste o que o processo precisa receber para funcionar.
B24: Passo 6 | C24: Coluna S: na mesma linha de cada entrada, escreva quem a fornece.
B25: Passo 7 | C25: Aba Requisitos: registre o que se exige de cada entrada e o que cada cliente exige de cada saída.
B26: Passo 8 | C26: Aba Checklist: valide o SIPOC com quem executa o processo e com o dono do processo.
B27: Passo 9 | C27: Aba Oportunidades: registre lacunas e problemas percebidos durante o mapeamento.
B29: Abas da planilha
B30: SIPOC | C30: Modelo principal. Cabeçalho do processo, tabela com as cinco colunas e resumo automático.
B31: Requisitos | C31: Puxa entradas e saídas da aba SIPOC e pede o requisito, o indicador e a meta de cada uma.
B32: Checklist | C32: Doze verificações de qualidade do SIPOC, com percentual de conclusão.
B33: Oportunidades | C33: Registro de lacunas e ações de melhoria, com contagem por status.
B34: Exemplo 1 - Pizzaria | C34: SIPOC preenchido de um processo simples: atender pedido de delivery.
B35: Exemplo 2 - Compras | C35: SIPOC preenchido de um processo corporativo: adquirir materiais e serviços.
B37: Regras e premissas do modelo
B38: Macroetapas | C38: O aviso da coluna P considera adequado ter de 4 a 7 etapas. É a faixa usual da prática de SIPOC; acima disso, o mapa começa a virar fluxograma.
B39: Alinhamento | C39: Os avisos comparam a quantidade de itens entre S e I e entre O e C, supondo um fornecedor por entrada e um cliente por saída na mesma linha. Repita o nome quando um mesmo fornecedor ou cliente aparecer em mais de uma linha.
B40: Capacidade | C40: A tabela comporta 12 linhas. Se faltar espaço, o processo provavelmente está detalhado demais para um SIPOC: agrupe itens.
B41: Exemplos | C41: Os dados das abas de exemplo são ilustrativos, criados para este material.

Sheet SIPOC
B1: SIPOC — Mapeamento de processo
B2: Preencha as células em amarelo-claro. As células cinza são calculadas automaticamente.
B4: Nome do processo | F4: Dono do processo
B5: Área / unidade | F5: Data
B6: Elaborado por | F6: Versão
B7: Objetivo do processo
B8: Início (gatilho)
B9: Fim (entrega final)
B10: Fora do escopo
C12: S | D12: I | E12: P | F12: O | G12: C
B13: # | C13: Fornecedores (Suppliers) | D13: Entradas (Inputs) | E13: Processo (Process) | F13: Saídas (Outputs) | G13: Clientes (Customers)
C14: Quem fornece cada entrada? | D14: O que o processo recebe para funcionar? | E14: Quais são as macroetapas? (4 a 7, verbo + objeto) | F14: O que o processo entrega? | G14: Quem recebe cada saída?
B15: Ex. | C15: Fornecedor de ingredientes | D15: Ingredientes dentro da validade | E15: Preparar e assar a pizza | F15: Pizza pronta conforme o pedido | G15: Cliente final
B16: 1
B17: 2
B18: 3
B19: 4
B20: 5
B21: 6
B22: 7
B23: 8
B24: 9
B25: 10
B26: 11
B27: 12
B29: Resumo automático
B30: Qtd. | C30: =COUNTA(C16:C27) -> 0 | D30: =COUNTA(D16:D27) -> 0 | E30: =COUNTA(E16:E27) -> 0 | F30: =COUNTA(F16:F27) -> 0 | G30: =COUNTA(G16:G27) -> 0
B31: Aviso | C31: =IF(C30=0,"Liste os fornecedores",IF(C30<D30,"Há entradas sem fornecedor na mesma linha","OK")) -> Liste os fornecedores | D31: =IF(D30=0,"Liste as entradas",IF(D30<C30,"Há fornecedores sem entrada na mesma linha","OK")) -> Liste as entradas | E31: =IF(E30=0,"Liste as macroetapas",IF(E30<4,"Poucas etapas: confira se o processo está completo",IF(E30>7,"Muitas etapas: agrupe em 4 a 7 macroetapas","OK"))) -> Liste as macroetapas | F31: =IF(F30=0,"Liste as saídas",IF(F30<G30,"Há clientes sem saída na mesma linha","OK")) -> Liste as saídas | G31: =IF(G30=0,"Liste os clientes",IF(G30<F30,"Há saídas sem cliente na mesma linha","OK")) -> Liste os clientes
B32: Campos do cabeçalho preenchidos (de 10) | F32: =COUNTA(D4,G4,D5,G5,D6,G6,D7,D8,D9,D10) -> 0

Sheet Requisitos
B1: Requisitos de entradas e saídas
B2: As colunas cinza vêm da aba SIPOC. Preencha as colunas em amarelo-claro.
B4: 1. Entradas: o que o processo exige de cada fornecedor
B5: # | C5: Fornecedor | D5: Entrada | E5: Requisito da entrada | F5: Como verificar | G5: Quem verifica | H5: Atende hoje?
B6: Ex. | C6: Fornecedor de ingredientes | D6: Ingredientes | E6: Dentro da validade e refrigerados até 5 °C | F6: Conferência no recebimento | G6: Auxiliar de cozinha | H6: Sim
B7: 1 | C7: =IF(SIPOC!C16="","",SIPOC!C16) | D7: =IF(SIPOC!D16="","",SIPOC!D16)
B8: 2 | C8: =IF(SIPOC!C17="","",SIPOC!C17) | D8: =IF(SIPOC!D17="","",SIPOC!D17)
B9: 3 | C9: =IF(SIPOC!C18="","",SIPOC!C18) | D9: =IF(SIPOC!D18="","",SIPOC!D18)
B10: 4 | C10: =IF(SIPOC!C19="","",SIPOC!C19) | D10: =IF(SIPOC!D19="","",SIPOC!D19)
B11: 5 | C11: =IF(SIPOC!C20="","",SIPOC!C20) | D11: =IF(SIPOC!D20="","",SIPOC!D20)
B12: 6 | C12: =IF(SIPOC!C21="","",SIPOC!C21) | D12: =IF(SIPOC!D21="","",SIPOC!D21)
B13: 7 | C13: =IF(SIPOC!C22="","",SIPOC!C22) | D13: =IF(SIPOC!D22="","",SIPOC!D22)
B14: 8 | C14: =IF(SIPOC!C23="","",SIPOC!C23) | D14: =IF(SIPOC!D23="","",SIPOC!D23)
B15: 9 | C15: =IF(SIPOC!C24="","",SIPOC!C24) | D15: =IF(SIPOC!D24="","",SIPOC!D24)
B16: 10 | C16: =IF(SIPOC!C25="","",SIPOC!C25) | D16: =IF(SIPOC!D25="","",SIPOC!D25)
B17: 11 | C17: =IF(SIPOC!C26="","",SIPOC!C26) | D17: =IF(SIPOC!D26="","",SIPOC!D26)
B18: 12 | C18: =IF(SIPOC!C27="","",SIPOC!C27) | D18: =IF(SIPOC!D27="","",SIPOC!D27)
B20: 2. Saídas: o que cada cliente exige do processo
B21: # | C21: Saída | D21: Cliente | E21: Requisito do cliente | F21: Indicador | G21: Meta | H21: Atende hoje?
B22: Ex. | C22: Pizza pronta conforme o pedido | D22: Cliente final | E22: Entrega em até 40 minutos | F22: % de entregas no prazo | G22: 95% ou mais | H22: Parcial
B23: 1 | C23: =IF(SIPOC!F16="","",SIPOC!F16) | D23: =IF(SIPOC!G16="","",SIPOC!G16)
B24: 2 | C24: =IF(SIPOC!F17="","",SIPOC!F17) | D24: =IF(SIPOC!G17="","",SIPOC!G17)
B25: 3 | C25: =IF(SIPOC!F18="","",SIPOC!F18) | D25: =IF(SIPOC!G18="","",SIPOC!G18)
B26: 4 | C26: =IF(SIPOC!F19="","",SIPOC!F19) | D26: =IF(SIPOC!G19="","",SIPOC!G19)
B27: 5 | C27: =IF(SIPOC!F20="","",SIPOC!F20) | D27: =IF(SIPOC!G20="","",SIPOC!G20)
B28: 6 | C28: =IF(SIPOC!F21="","",SIPOC!F21) | D28: =IF(SIPOC!G21="","",SIPOC!G21)
B29: 7 | C29: =IF(SIPOC!F22="","",SIPOC!F22) | D29: =IF(SIPOC!G22="","",SIPOC!G22)
B30: 8 | C30: =IF(SIPOC!F23="","",SIPOC!F23) | D30: =IF(SIPOC!G23="","",SIPOC!G23)
B31: 9 | C31: =IF(SIPOC!F24="","",SIPOC!F24) | D31: =IF(SIPOC!G24="","",SIPOC!G24)
B32: 10 | C32: =IF(SIPOC!F25="","",SIPOC!F25) | D32: =IF(SIPOC!G25="","",SIPOC!G25)
B33: 11 | C33: =IF(SIPOC!F26="","",SIPOC!F26) | D33: =IF(SIPOC!G26="","",SIPOC!G26)
B34: 12 | C34: =IF(SIPOC!F27="","",SIPOC!F27) | D34: =IF(SIPOC!G27="","",SIPOC!G27)
B36: Resumo automático
B37: Requisitos de entrada definidos | F37: =COUNTA(E7:E18) -> 0
B38: Requisitos de saída definidos | F38: =COUNTA(E23:E34) -> 0
B39: Requisitos atendidos (Sim) | F39: =COUNTIF(H7:H18,"Sim")+COUNTIF(H23:H34,"Sim") -> 0
B40: Requisitos parciais ou não atendidos | F40: =COUNTIF(H7:H18,"Parcial")+COUNTIF(H7:H18,"Não")+COUNTIF(H23:H34,"Parcial")+COUNTIF(H23:H34,"Não") -> 0

Sheet Checklist
B1: Checklist de validação do SIPOC
B2: Escolha o status de cada item na lista suspensa (coluna em amarelo-claro).
B4: # | C4: Item de verificação | D4: Status | E4: Observações
B5: 1 | C5: O processo tem nome claro, no formato verbo + objeto.
B6: 2 | C6: Os limites estão definidos: evento de início (gatilho) e entrega final.
B7: 3 | C7: O processo tem de 4 a 7 macroetapas.
B8: 4 | C8: Cada etapa começa com verbo no infinitivo e descreve o que é feito, não quem faz.
B9: 5 | C9: As etapas retratam o processo como ele é hoje, não como deveria ser.
B10: 6 | C10: Toda saída tem pelo menos um cliente identificado.
B11: 7 | C11: Clientes internos e externos foram considerados.
B12: 8 | C12: Toda entrada tem pelo menos um fornecedor identificado.
B13: 9 | C13: Toda entrada é usada por alguma etapa do processo.
B14: 10 | C14: Os requisitos das principais saídas foram levantados com os clientes.
B15: 11 | C15: O SIPOC foi construído com a participação de quem executa o processo.
B16: 12 | C16: O dono do processo validou o resultado.
B18: Resumo automático
B19: Itens atendidos (Sim) | D19: =COUNTIF(D5:D16,"Sim") -> 0
B20: Itens parciais | D20: =COUNTIF(D5:D16,"Parcial") -> 0
B21: Itens não atendidos | D21: =COUNTIF(D5:D16,"Não") -> 0
B22: Itens sem resposta | D22: =COUNTBLANK(D5:D16) -> 12
B23: Percentual atendido | D23: =D19/ROWS(D5:D16) -> 0
B24: Situação | D24: =IF(D19=ROWS(D5:D16),"Validado",IF(D22>0,"Em andamento","Com pendências")) -> Em andamento

Sheet Oportunidades
B1: Oportunidades de melhoria
B2: Registre aqui as lacunas percebidas durante o mapeamento. Preencha as células em amarelo-claro.
B4: # | C4: Lacuna ou problema observado | D4: Elemento | E4: Impacto | F4: Ação proposta | G4: Responsável | H4: Prazo | I4: Status
B5: Ex. | C5: Pedidos chegam sem o complemento do endereço | D5: Entrada | E5: Alto | F5: Tornar o campo obrigatório no formulário de pedido | G5: Gerente da loja | H5: 46325 | I5: Aberta
B6: 1
B7: 2
B8: 3
B9: 4
B10: 5
B11: 6
B12: 7
B13: 8
B14: 9
B15: 10
B16: 11
B17: 12
... B20: 15
B22: Resumo automático
B23: Oportunidades registradas | G23: =COUNTA(C6:C20) -> 0
B24: Abertas | G24: =COUNTIF(I6:I20,"Aberta") -> 0
B25: Em andamento | G25: =COUNTIF(I6:I20,"Em andamento") -> 0
B26: Concluídas | G26: =COUNTIF(I6:I20,"Concluída") -> 0
B27: Alto impacto ainda não concluídas | G27: =COUNTIFS(E6:E20,"Alto",I6:I20,"<>Concluída") -> 0

Sheet Exemplo 1 - Pizzaria
B1: SIPOC — Mapeamento de processo
B2: Exemplo preenchido, para consulta. Use a aba SIPOC para o seu processo.
B4: Nome do processo | D4: Atender pedido de delivery | F4: Dono do processo | G4: Gerente da loja
B5: Área / unidade | D5: Pizzaria (loja) | F5: Data | G5: 46293
B6: Elaborado por | D6: Equipe da loja | F6: Versão | G6: 1.0
B7: Objetivo do processo | D7: Entregar ao cliente a pizza certa, quente e no prazo combinado.
B8: Início (gatilho) | D8: Cliente confirma o pedido (telefone ou aplicativo).
B9: Fim (entrega final) | D9: Pizza entregue e pagamento confirmado.
B10: Fora do escopo | D10: Compra de ingredientes, atendimento no salão e pós-venda.
C12: S | D12: I | E12: P | F12: O | G12: C
B13: # | C13: Fornecedores (Suppliers) | D13: Entradas (Inputs) | E13: Processo (Process) | F13: Saídas (Outputs) | G13: Clientes (Customers)
C14: Quem fornece cada entrada? | D14: O que o processo recebe para funcionar? | E14: Quais são as macroetapas? (4 a 7, verbo + objeto) | F14: O que o processo entrega? | G14: Quem recebe cada saída?
B15: Leia na horizontal: cada entrada está na linha do seu fornecedor; cada saída, na linha do seu cliente. As etapas do processo seguem a ordem de execução.
B16: 1 | C16: Cliente | D16: Pedido: sabor, tamanho, endereço e forma de pagamento | E16: Registrar o pedido | F16: Pizza quente, conforme o pedido | G16: Cliente final
B17: 2 | C17: Aplicativo de delivery | D17: Dados do pedido e confirmação de pagamento | E17: Montar a pizza | F17: Comprovante ou nota fiscal | G17: Cliente final
B18: 3 | C18: Fornecedor de ingredientes | D18: Massa, molho, queijo e recheios | E18: Assar | F18: Pagamento recebido | G18: Caixa da pizzaria
B19: 4 | C19: Fabricante de embalagens | D19: Caixas de pizza | E19: Embalar e conferir | F19: Status do pedido atualizado | G19: Aplicativo de delivery
B20: 5 | C20: Distribuidora de gás | D20: Gás para o forno | E20: Entregar ao cliente | F20: Registro de tempos de preparo e entrega | G20: Gerente da loja
B21: 6 | C21: Entregador parceiro | D21: Disponibilidade para a rota | E21: Confirmar o pagamento
B22: 7
B23: 8
B24: 9
B25: 10
B26: 11
B27: 12
B29: Resumo automático
B30: Qtd. | C30: =COUNTA(C16:C27) -> 6 | D30: =COUNTA(D16:D27) -> 6 | E30: =COUNTA(E16:E27) -> 6 | F30: =COUNTA(F16:F27) -> 5 | G30: =COUNTA(G16:G27) -> 5
B31: Aviso | C31: =IF(C30=0,"Liste os fornecedores",IF(C30<D30,"Há entradas sem fornecedor na mesma linha","OK")) -> OK | D31: =IF(D30=0,"Liste as entradas",IF(D30<C30,"Há fornecedores sem entrada na mesma linha","OK")) -> OK | E31: =IF(E30=0,"Liste as macroetapas",IF(E30<4,"Poucas etapas: confira se o processo está completo",IF(E30>7,"Muitas etapas: agrupe em 4 a 7 macroetapas","OK"))) -> OK | F31: =IF(F30=0,"Liste as saídas",IF(F30<G30,"Há clientes sem saída na mesma linha","OK")) -> OK | G31: =IF(G30=0,"Liste os clientes",IF(G30<F30,"Há saídas sem cliente na mesma linha","OK")) -> OK
B32: Campos do cabeçalho preenchidos (de 10) | F32: =COUNTA(D4,G4,D5,G5,D6,G6,D7,D8,D9,D10) -> 10

Sheet Exemplo 2 - Compras
B1: SIPOC — Mapeamento de processo
B2: Exemplo preenchido, para consulta. Use a aba SIPOC para o seu processo.
B4: Nome do processo | D4: Adquirir materiais e serviços | F4: Dono do processo | G4: Gerente de Suprimentos
B5: Área / unidade | D5: Suprimentos | F5: Data | G5: 46293
B6: Elaborado por | D6: Equipe de Suprimentos | F6: Versão | G6: 1.0
B7: Objetivo do processo | D7: Atender às necessidades das áreas com o item certo, no prazo, ao melhor custo total e dentro da política de compras.
B8: Início (gatilho) | D8: Requisição de compra aprovada pelo gestor da área.
B9: Fim (entrega final) | D9: Item recebido, conferido e nota fiscal liberada para pagamento.
B10: Fora do escopo | D10: Homologação de novos fornecedores, pagamento e gestão de estoque.
C12: S | D12: I | E12: P | F12: O | G12: C
B13: # | C13: Fornecedores (Suppliers) | D13: Entradas (Inputs) | E13: Processo (Process) | F13: Saídas (Outputs) | G13: Clientes (Customers)
C14: Quem fornece cada entrada? | D14: O que o processo recebe para funcionar? | E14: Quais são as macroetapas? (4 a 7, verbo + objeto) | F14: O que o processo entrega? | G14: Quem recebe cada saída?
B15: Leia na horizontal: cada entrada está na linha do seu fornecedor; cada saída, na linha do seu cliente. As etapas do processo seguem a ordem de execução.
B16: 1 | C16: Área requisitante | D16: Requisição de compra com especificação técnica | E16: Analisar a requisição | F16: Pedido de compra ou contrato emitido | G16: Fornecedor selecionado
B17: 2 | C17: Fornecedores homologados | D17: Propostas comerciais | E17: Cotar com fornecedores | F17: Material ou serviço entregue conforme a especificação | G17: Área requisitante
B18: 3 | C18: Controladoria | D18: Orçamento disponível no centro de custo | E18: Negociar e selecionar a proposta | F18: Nota fiscal conferida e liberada | G18: Contas a pagar
B19: 4 | C19: Jurídico | D19: Minutas contratuais padrão | E19: Emitir o pedido de compra ou contrato | F19: Avaliação de desempenho do fornecedor | G19: Gestão de fornecedores
B20: 5 | C20: Diretoria | D20: Política de compras e alçadas de aprovação | E20: Receber e conferir o item | F20: Registro da economia obtida na negociação | G20: Controladoria
B21: 6 | E21: Liberar a nota fiscal para pagamento
B22: 7
B23: 8
B24: 9
B25: 10
B26: 11
B27: 12
B29: Resumo automático
B30: Qtd. | C30: =COUNTA(C16:C27) -> 5 | D30: =COUNTA(D16:D27) -> 5 | E30: =COUNTA(E16:E27) -> 6 | F30: =COUNTA(F16:F27) -> 5 | G30: =COUNTA(G16:G27) -> 5
B31: Aviso | C31: =IF(C30=0,"Liste os fornecedores",IF(C30<D30,"Há entradas sem fornecedor na mesma linha","OK")) -> OK | D31: =IF(D30=0,"Liste as entradas",IF(D30<C30,"Há fornecedores sem entrada na mesma linha","OK")) -> OK | E31: =IF(E30=0,"Liste as macroetapas",IF(E30<4,"Poucas etapas: confira se o processo está completo",IF(E30>7,"Muitas etapas: agrupe em 4 a 7 macroetapas","OK"))) -> OK | F31: =IF(F30=0,"Liste as saídas",IF(F30<G30,"Há clientes sem saída na mesma linha","OK")) -> OK | G31: =IF(G30=0,"Liste os clientes",IF(G30<F30,"Há saídas sem cliente na mesma linha","OK")) -> OK
B32: Campos do cabeçalho preenchidos (de 10) | F32: =COUNTA(D4,G4,D5,G5,D6,G6,D7,D8,D9,D10) -> 10
