Workbook

Sheet Instruções
B1: Matriz de riscos — Como usar esta planilha
B2: Modelo para descrever os riscos, avaliar o nível, definir a resposta e acompanhar o risco residual.
B4: Legenda: onde preencher
B5: Amarelo-claro | C5: Células de entrada. É aqui que você digita.
B6: Cinza | C6: Células calculadas ou fixas (rótulos, pontos, níveis, avisos). Não altere.
B7: Cinza em itálico | C7: Linha de exemplo (marcada com “Ex.”). Mostra o formato esperado e não entra nas contagens.
B8: Listas suspensas | C8: Colunas de resposta, decisão e status aceitam apenas as opções da lista. As notas aceitam números inteiros de 1 a 5.
B9: Comentários | C9: Células com triângulo vermelho no canto trazem uma dica de preenchimento. Passe o mouse sobre elas.
B11: Os quatro níveis
B12: Baixo | C12: De 1 a 4 pontos. Aceitar e acompanhar na revisão anual.
B13: Médio | C13: De 5 a 9 pontos. Tratar quando o custo compensar. Revisar a cada seis meses.
B14: Alto | C14: De 10 a 16 pontos. Tratar, com ação, responsável e prazo.
B15: Crítico | C15: De 20 a 25 pontos. Tratar de imediato, com decisão da direção.
B17: Ordem recomendada de preenchimento
B18: Passo 1 | C18: Aba Escalas: leia as descrições das notas e combine com o grupo como usá-las.
B19: Passo 2 | C19: Aba Riscos: preencha o cabeçalho e descreva cada risco com causa, evento e consequência.
B20: Passo 3 | C20: Aba Riscos: dê as notas de probabilidade e de impacto, e leia os pontos e o nível.
B21: Passo 4 | C21: Aba Riscos: escolha a resposta e escreva a ação, o responsável e o prazo. Se a resposta for aceitar, escreva a justificativa.
B22: Passo 5 | C22: Aba Riscos: estime a probabilidade e o impacto residuais, já contando com a ação.
B23: Passo 6 | C23: Aba Mapa: compare a matriz inicial com a residual e leia o resumo.
B24: Passo 7 | C24: Aba Oportunidades: registre as oportunidades do processo. Aba Checklist: valide a matriz.
B26: Abas da planilha
B27: Riscos | C27: Registro dos riscos, com análise, resposta, risco residual, conferência e alertas.
B28: Mapa | C28: As duas matrizes, inicial e residual, com contagem por nível, resumo e gráfico.
B29: Oportunidades | C29: Registro das oportunidades, com probabilidade, benefício, prioridade e ação.
B30: Escalas | C30: Descrição das notas de probabilidade, de impacto e de benefício, dos níveis e das respostas.
B31: Checklist | C31: Doze verificações de qualidade da matriz, com percentual de conclusão.
B32: Exemplo 1 - Pizzaria | C32: Riscos do processo de delivery de uma organização pequena.
B33: Exemplo 2 - Compras | C33: Riscos do processo de aquisição de uma indústria.
B35: Regras e premissas do modelo
B36: Pontos e nível | C36: Pontos = probabilidade × impacto. De 1 a 4, baixo. De 5 a 9, médio. De 10 a 16, alto. De 20 a 25, crítico. As escalas e as faixas são uma convenção deste modelo.
B37: Impacto 5 | C37: A multiplicação trata como iguais um risco raro e grave e um risco frequente e leve. Por isso, a coluna Alerta avisa quando o impacto é 5, qualquer que seja o nível.
B38: Risco residual | C38: É uma estimativa, feita ao definir a resposta. Depois que a ação estiver implantada, confira com fatos e ajuste as notas.
B39: Risco aceito | C39: Na resposta Aceitar, escreva a justificativa na coluna da ação e repita as notas iniciais nas colunas residuais.
B40: Situação | C40: Uma ação é considerada atrasada quando o prazo é anterior à data de hoje e ela ainda não foi concluída.
B41: Exemplos | C41: Os dados das abas de exemplo são ilustrativos, criados para este material.

Sheet Riscos
B1: Matriz de riscos
B2: Um risco por linha. Preencha as células em amarelo-claro. As células cinza são calculadas.
B4: Organização | G4: Processo | P4: Data da análise
B5: Objetivo do processo | G5: Participantes | P5: Data da revisão
B7: Identificação | G7: Análise | K7: Resposta | P7: Risco residual | T7: Acompanhamento
B8: # | C8: Processo ou etapa | D8: Causa | E8: Evento | F8: Consequência | G8: P | H8: I | I8: Pontos | J8: Nível | K8: Resposta | L8: Ação ou justificativa | M8: Responsável | N8: Prazo | O8: Status | P8: P | Q8: I | R8: Pontos | S8: Nível | T8: Situação | U8: Conferência | V8: Alerta
C9: Onde o risco nasce | D9: O que existe hoje | E9: O que pode acontecer | F9: O efeito sobre o objetivo | G9: 1 a 5 | H9: 1 a 5 | I9: P × I | J9: Faixa | K9: Escolha na lista | L9: Verbo no infinitivo | M9: Cargo ou nome | N9: Data | O9: Da ação | P9: 1 a 5 | Q9: 1 a 5 | R9: P × I | S9: Faixa | T9: Calculada | U9: Campos da linha | V9: Pontos de atenção
B10: Ex. | C10: Planejamento de compras | D10: Um só fornecedor de resina | E10: O fornecedor deixa de entregar | F10: Parada da produção por falta de material | G10: 4 | H10: 5 | I10: 20 | J10: Crítico | K10: Reduzir | L10: Homologar um segundo fornecedor e manter estoque mínimo de 15 dias. | M10: Gerente de Suprimentos | N10: 46374 | O10: Em andamento | P10: 2 | Q10: 3 | R10: 6 | S10: Médio | T10: No prazo | U10: Completo | V10: Impacto 5: tenha plano de contingência
B11: 1 | I11: =IF(OR(G11="",H11=""),"",G11*H11) | J11: =IF(I11="","",IF(I11>=20,"Crítico",IF(I11>=10,"Alto",IF(I11>=5,"Médio","Baixo")))) | R11: =IF(OR(P11="",Q11=""),"",P11*Q11) | S11: =IF(R11="","",IF(R11>=20,"Crítico",IF(R11>=10,"Alto",IF(R11>=5,"Médio","Baixo")))) | T11: =IF(OR(E11="",K11=""),"",IF(K11="Aceitar","Aceito",IF(O11="Concluída","Concluída",IF(N11="","Sem prazo",IF(N11<TODAY(),"Atrasada","No prazo"))))) | U11: =IF(E11="","",IF(OR(D11="",F11=""),"Descreva a causa e a consequência",IF(I11="","Faltam as notas de P e I",IF(K11="","Escolha a resposta",IF(L11="",IF(K11="Aceitar","Justifique a decisão de aceitar","Escreva a ação"),IF(AND(K11<>"Aceitar",OR(M11="",N11="")),"Falta responsável ou prazo",IF(R11="","Avalie o risco residual",IF(R11>I11,"Residual maior que o inicial","Completo")))))))) | V11: =IF(I11="","",IF(AND(OR(J11="Alto",J11="Crítico"),K11="Aceitar"),"Risco alto aceito: peça a decisão da direção",IF(OR(S11="Alto",S11="Crítico"),"Residual ainda alto: reforce a resposta",IF(OR(H11=5,Q11=5),"Impacto 5: tenha plano de contingência",""))))
B12: 2 | I12: =IF(OR(G12="",H12=""),"",G12*H12) | J12: =IF(I12="","",IF(I12>=20,"Crítico",IF(I12>=10,"Alto",IF(I12>=5,"Médio","Baixo")))) | R12: =IF(OR(P12="",Q12=""),"",P12*Q12) | S12: =IF(R12="","",IF(R12>=20,"Crítico",IF(R12>=10,"Alto",IF(R12>=5,"Médio","Baixo")))) | T12: =IF(OR(E12="",K12=""),"",IF(K12="Aceitar","Aceito",IF(O12="Concluída","Concluída",IF(N12="","Sem prazo",IF(N12<TODAY(),"Atrasada","No prazo"))))) | U12: =IF(E12="","",IF(OR(D12="",F12=""),"Descreva a causa e a consequência",IF(I12="","Faltam as notas de P e I",IF(K12="","Escolha a resposta",IF(L12="",IF(K12="Aceitar","Justifique a decisão de aceitar","Escreva a ação"),IF(AND(K12<>"Aceitar",OR(M12="",N12="")),"Falta responsável ou prazo",IF(R12="","Avalie o risco residual",IF(R12>I12,"Residual maior que o inicial","Completo")))))))) | V12: =IF(I12="","",IF(AND(OR(J12="Alto",J12="Crítico"),K12="Aceitar"),"Risco alto aceito: peça a decisão da direção",IF(OR(S12="Alto",S12="Crítico"),"Residual ainda alto: reforce a resposta",IF(OR(H12=5,Q12=5),"Impacto 5: tenha plano de contingência",""))))
B13: 3 | I13: =IF(OR(G13="",H13=""),"",G13*H13) | J13: =IF(I13="","",IF(I13>=20,"Crítico",IF(I13>=10,"Alto",IF(I13>=5,"Médio","Baixo")))) | R13: =IF(OR(P13="",Q13=""),"",P13*Q13) | S13: =IF(R13="","",IF(R13>=20,"Crítico",IF(R13>=10,"Alto",IF(R13>=5,"Médio","Baixo")))) | T13: =IF(OR(E13="",K13=""),"",IF(K13="Aceitar","Aceito",IF(O13="Concluída","Concluída",IF(N13="","Sem prazo",IF(N13<TODAY(),"Atrasada","No prazo"))))) | U13: =IF(E13="","",IF(OR(D13="",F13=""),"Descreva a causa e a consequência",IF(I13="","Faltam as notas de P e I",IF(K13="","Escolha a resposta",IF(L13="",IF(K13="Aceitar","Justifique a decisão de aceitar","Escreva a ação"),IF(AND(K13<>"Aceitar",OR(M13="",N13="")),"Falta responsável ou prazo",IF(R13="","Avalie o risco residual",IF(R13>I13,"Residual maior que o inicial","Completo")))))))) | V13: =IF(I13="","",IF(AND(OR(J13="Alto",J13="Crítico"),K13="Aceitar"),"Risco alto aceito: peça a decisão da direção",IF(OR(S13="Alto",S13="Crítico"),"Residual ainda alto: reforce a resposta",IF(OR(H13=5,Q13=5),"Impacto 5: tenha plano de contingência",""))))
B14: 4 | I14: =IF(OR(G14="",H14=""),"",G14*H14) | J14: =IF(I14="","",IF(I14>=20,"Crítico",IF(I14>=10,"Alto",IF(I14>=5,"Médio","Baixo")))) | R14: =IF(OR(P14="",Q14=""),"",P14*Q14) | S14: =IF(R14="","",IF(R14>=20,"Crítico",IF(R14>=10,"Alto",IF(R14>=5,"Médio","Baixo")))) | T14: =IF(OR(E14="",K14=""),"",IF(K14="Aceitar","Aceito",IF(O14="Concluída","Concluída",IF(N14="","Sem prazo",IF(N14<TODAY(),"Atrasada","No prazo"))))) | U14: =IF(E14="","",IF(OR(D14="",F14=""),"Descreva a causa e a consequência",IF(I14="","Faltam as notas de P e I",IF(K14="","Escolha a resposta",IF(L14="",IF(K14="Aceitar","Justifique a decisão de aceitar","Escreva a ação"),IF(AND(K14<>"Aceitar",OR(M14="",N14="")),"Falta responsável ou prazo",IF(R14="","Avalie o risco residual",IF(R14>I14,"Residual maior que o inicial","Completo")))))))) | V14: =IF(I14="","",IF(AND(OR(J14="Alto",J14="Crítico"),K14="Aceitar"),"Risco alto aceito: peça a decisão da direção",IF(OR(S14="Alto",S14="Crítico"),"Residual ainda alto: reforce a resposta",IF(OR(H14=5,Q14=5),"Impacto 5: tenha plano de contingência",""))))
B15: 5 | I15: =IF(OR(G15="",H15=""),"",G15*H15) | J15: =IF(I15="","",IF(I15>=20,"Crítico",IF(I15>=10,"Alto",IF(I15>=5,"Médio","Baixo")))) | R15: =IF(OR(P15="",Q15=""),"",P15*Q15) | S15: =IF(R15="","",IF(R15>=20,"Crítico",IF(R15>=10,"Alto",IF(R15>=5,"Médio","Baixo")))) | T15: =IF(OR(E15="",K15=""),"",IF(K15="Aceitar","Aceito",IF(O15="Concluída","Concluída",IF(N15="","Sem prazo",IF(N15<TODAY(),"Atrasada","No prazo"))))) | U15: =IF(E15="","",IF(OR(D15="",F15=""),"Descreva a causa e a consequência",IF(I15="","Faltam as notas de P e I",IF(K15="","Escolha a resposta",IF(L15="",IF(K15="Aceitar","Justifique a decisão de aceitar","Escreva a ação"),IF(AND(K15<>"Aceitar",OR(M15="",N15="")),"Falta responsável ou prazo",IF(R15="","Avalie o risco residual",IF(R15>I15,"Residual maior que o inicial","Completo")))))))) | V15: =IF(I15="","",IF(AND(OR(J15="Alto",J15="Crítico"),K15="Aceitar"),"Risco alto aceito: peça a decisão da direção",IF(OR(S15="Alto",S15="Crítico"),"Residual ainda alto: reforce a resposta",IF(OR(H15=5,Q15=5),"Impacto 5: tenha plano de contingência",""))))
B16: 6 | I16: =IF(OR(G16="",H16=""),"",G16*H16) | J16: =IF(I16="","",IF(I16>=20,"Crítico",IF(I16>=10,"Alto",IF(I16>=5,"Médio","Baixo")))) | R16: =IF(OR(P16="",Q16=""),"",P16*Q16) | S16: =IF(R16="","",IF(R16>=20,"Crítico",IF(R16>=10,"Alto",IF(R16>=5,"Médio","Baixo")))) | T16: =IF(OR(E16="",K16=""),"",IF(K16="Aceitar","Aceito",IF(O16="Concluída","Concluída",IF(N16="","Sem prazo",IF(N16<TODAY(),"Atrasada","No prazo"))))) | U16: =IF(E16="","",IF(OR(D16="",F16=""),"Descreva a causa e a consequência",IF(I16="","Faltam as notas de P e I",IF(K16="","Escolha a resposta",IF(L16="",IF(K16="Aceitar","Justifique a decisão de aceitar","Escreva a ação"),IF(AND(K16<>"Aceitar",OR(M16="",N16="")),"Falta responsável ou prazo",IF(R16="","Avalie o risco residual",IF(R16>I16,"Residual maior que o inicial","Completo")))))))) | V16: =IF(I16="","",IF(AND(OR(J16="Alto",J16="Crítico"),K16="Aceitar"),"Risco alto aceito: peça a decisão da direção",IF(OR(S16="Alto",S16="Crítico"),"Residual ainda alto: reforce a resposta",IF(OR(H16=5,Q16=5),"Impacto 5: tenha plano de contingência",""))))
B17: 7 | I17: =IF(OR(G17="",H17=""),"",G17*H17) | J17: =IF(I17="","",IF(I17>=20,"Crítico",IF(I17>=10,"Alto",IF(I17>=5,"Médio","Baixo")))) | R17: =IF(OR(P17="",Q17=""),"",P17*Q17) | S17: =IF(R17="","",IF(R17>=20,"Crítico",IF(R17>=10,"Alto",IF(R17>=5,"Médio","Baixo")))) | T17: =IF(OR(E17="",K17=""),"",IF(K17="Aceitar","Aceito",IF(O17="Concluída","Concluída",IF(N17="","Sem prazo",IF(N17<TODAY(),"Atrasada","No prazo"))))) | U17: =IF(E17="","",IF(OR(D17="",F17=""),"Descreva a causa e a consequência",IF(I17="","Faltam as notas de P e I",IF(K17="","Escolha a resposta",IF(L17="",IF(K17="Aceitar","Justifique a decisão de aceitar","Escreva a ação"),IF(AND(K17<>"Aceitar",OR(M17="",N17="")),"Falta responsável ou prazo",IF(R17="","Avalie o risco residual",IF(R17>I17,"Residual maior que o inicial","Completo")))))))) | V17: =IF(I17="","",IF(AND(OR(J17="Alto",J17="Crítico"),K17="Aceitar"),"Risco alto aceito: peça a decisão da direção",IF(OR(S17="Alto",S17="Crítico"),"Residual ainda alto: reforce a resposta",IF(OR(H17=5,Q17=5),"Impacto 5: tenha plano de contingência",""))))
B18: 8 | I18: =IF(OR(G18="",H18=""),"",G18*H18) | J18: =IF(I18="","",IF(I18>=20,"Crítico",IF(I18>=10,"Alto",IF(I18>=5,"Médio","Baixo")))) | R18: =IF(OR(P18="",Q18=""),"",P18*Q18) | S18: =IF(R18="","",IF(R18>=20,"Crítico",IF(R18>=10,"Alto",IF(R18>=5,"Médio","Baixo")))) | T18: =IF(OR(E18="",K18=""),"",IF(K18="Aceitar","Aceito",IF(O18="Concluída","Concluída",IF(N18="","Sem prazo",IF(N18<TODAY(),"Atrasada","No prazo"))))) | U18: =IF(E18="","",IF(OR(D18="",F18=""),"Descreva a causa e a consequência",IF(I18="","Faltam as notas de P e I",IF(K18="","Escolha a resposta",IF(L18="",IF(K18="Aceitar","Justifique a decisão de aceitar","Escreva a ação"),IF(AND(K18<>"Aceitar",OR(M18="",N18="")),"Falta responsável ou prazo",IF(R18="","Avalie o risco residual",IF(R18>I18,"Residual maior que o inicial","Completo")))))))) | V18: =IF(I18="","",IF(AND(OR(J18="Alto",J18="Crítico"),K18="Aceitar"),"Risco alto aceito: peça a decisão da direção",IF(OR(S18="Alto",S18="Crítico"),"Residual ainda alto: reforce a resposta",IF(OR(H18=5,Q18=5),"Impacto 5: tenha plano de contingência",""))))
B19: 9 | I19: =IF(OR(G19="",H19=""),"",G19*H19) | J19: =IF(I19="","",IF(I19>=20,"Crítico",IF(I19>=10,"Alto",IF(I19>=5,"Médio","Baixo")))) | R19: =IF(OR(P19="",Q19=""),"",P19*Q19) | S19: =IF(R19="","",IF(R19>=20,"Crítico",IF(R19>=10,"Alto",IF(R19>=5,"Médio","Baixo")))) | T19: =IF(OR(E19="",K19=""),"",IF(K19="Aceitar","Aceito",IF(O19="Concluída","Concluída",IF(N19="","Sem prazo",IF(N19<TODAY(),"Atrasada","No prazo"))))) | U19: =IF(E19="","",IF(OR(D19="",F19=""),"Descreva a causa e a consequência",IF(I19="","Faltam as notas de P e I",IF(K19="","Escolha a resposta",IF(L19="",IF(K19="Aceitar","Justifique a decisão de aceitar","Escreva a ação"),IF(AND(K19<>"Aceitar",OR(M19="",N19="")),"Falta responsável ou prazo",IF(R19="","Avalie o risco residual",IF(R19>I19,"Residual maior que o inicial","Completo")))))))) | V19: =IF(I19="","",IF(AND(OR(J19="Alto",J19="Crítico"),K19="Aceitar"),"Risco alto aceito: peça a decisão da direção",IF(OR(S19="Alto",S19="Crítico"),"Residual ainda alto: reforce a resposta",IF(OR(H19=5,Q19=5),"Impacto 5: tenha plano de contingência",""))))
B20: 10 | I20: =IF(OR(G20="",H20=""),"",G20*H20) | J20: =IF(I20="","",IF(I20>=20,"Crítico",IF(I20>=10,"Alto",IF(I20>=5,"Médio","Baixo")))) | R20: =IF(OR(P20="",Q20=""),"",P20*Q20) | S20: =IF(R20="","",IF(R20>=20,"Crítico",IF(R20>=10,"Alto",IF(R20>=5,"Médio","Baixo")))) | T20: =IF(OR(E20="",K20=""),"",IF(K20="Aceitar","Aceito",IF(O20="Concluída","Concluída",IF(N20="","Sem prazo",IF(N20<TODAY(),"Atrasada","No prazo"))))) | U20: =IF(E20="","",IF(OR(D20="",F20=""),"Descreva a causa e a consequência",IF(I20="","Faltam as notas de P e I",IF(K20="","Escolha a resposta",IF(L20="",IF(K20="Aceitar","Justifique a decisão de aceitar","Escreva a ação"),IF(AND(K20<>"Aceitar",OR(M20="",N20="")),"Falta responsável ou prazo",IF(R20="","Avalie o risco residual",IF(R20>I20,"Residual maior que o inicial","Completo")))))))) | V20: =IF(I20="","",IF(AND(OR(J20="Alto",J20="Crítico"),K20="Aceitar"),"Risco alto aceito: peça a decisão da direção",IF(OR(S20="Alto",S20="Crítico"),"Residual ainda alto: reforce a resposta",IF(OR(H20=5,Q20=5),"Impacto 5: tenha plano de contingência",""))))
B21: 11 | I21: =IF(OR(G21="",H21=""),"",G21*H21) | J21: =IF(I21="","",IF(I21>=20,"Crítico",IF(I21>=10,"Alto",IF(I21>=5,"Médio","Baixo")))) | R21: =IF(OR(P21="",Q21=""),"",P21*Q21) | S21: =IF(R21="","",IF(R21>=20,"Crítico",IF(R21>=10,"Alto",IF(R21>=5,"Médio","Baixo")))) | T21: =IF(OR(E21="",K21=""),"",IF(K21="Aceitar","Aceito",IF(O21="Concluída","Concluída",IF(N21="","Sem prazo",IF(N21<TODAY(),"Atrasada","No prazo"))))) | U21: =IF(E21="","",IF(OR(D21="",F21=""),"Descreva a causa e a consequência",IF(I21="","Faltam as notas de P e I",IF(K21="","Escolha a resposta",IF(L21="",IF(K21="Aceitar","Justifique a decisão de aceitar","Escreva a ação"),IF(AND(K21<>"Aceitar",OR(M21="",N21="")),"Falta responsável ou prazo",IF(R21="","Avalie o risco residual",IF(R21>I21,"Residual maior que o inicial","Completo")))))))) | V21: =IF(I21="","",IF(AND(OR(J21="Alto",J21="Crítico"),K21="Aceitar"),"Risco alto aceito: peça a decisão da direção",IF(OR(S21="Alto",S21="Crítico"),"Residual ainda alto: reforce a resposta",IF(OR(H21=5,Q21=5),"Impacto 5: tenha plano de contingência",""))))
B22: 12 | I22: =IF(OR(G22="",H22=""),"",G22*H22) | J22: =IF(I22="","",IF(I22>=20,"Crítico",IF(I22>=10,"Alto",IF(I22>=5,"Médio","Baixo")))) | R22: =IF(OR(P22="",Q22=""),"",P22*Q22) | S22: =IF(R22="","",IF(R22>=20,"Crítico",IF(R22>=10,"Alto",IF(R22>=5,"Médio","Baixo")))) | T22: =IF(OR(E22="",K22=""),"",IF(K22="Aceitar","Aceito",IF(O22="Concluída","Concluída",IF(N22="","Sem prazo",IF(N22<TODAY(),"Atrasada","No prazo"))))) | U22: =IF(E22="","",IF(OR(D22="",F22=""),"Descreva a causa e a consequência",IF(I22="","Faltam as notas de P e I",IF(K22="","Escolha a resposta",IF(L22="",IF(K22="Aceitar","Justifique a decisão de aceitar","Escreva a ação"),IF(AND(K22<>"Aceitar",OR(M22="",N22="")),"Falta responsável ou prazo",IF(R22="","Avalie o risco residual",IF(R22>I22,"Residual maior que o inicial","Completo")))))))) | V22: =IF(I22="","",IF(AND(OR(J22="Alto",J22="Crítico"),K22="Aceitar"),"Risco alto aceito: peça a decisão da direção",IF(OR(S22="Alto",S22="Crítico"),"Residual ainda alto: reforce a resposta",IF(OR(H22=5,Q22=5),"Impacto 5: tenha plano de contingência",""))))
... B30: 20 | I30: =IF(OR(G30="",H30=""),"",G30*H30) | J30: =IF(I30="","",IF(I30>=20,"Crítico",IF(I30>=10,"Alto",IF(I30>=5,"Médio","Baixo")))) | R30: =IF(OR(P30="",Q30=""),"",P30*Q30) | S30: =IF(R30="","",IF(R30>=20,"Crítico",IF(R30>=10,"Alto",IF(R30>=5,"Médio","Baixo")))) | T30: =IF(OR(E30="",K30=""),"",IF(K30="Aceitar","Aceito",IF(O30="Concluída","Concluída",IF(N30="","Sem prazo",IF(N30<TODAY(),"Atrasada","No prazo"))))) | U30: =IF(E30="","",IF(OR(D30="",F30=""),"Descreva a causa e a consequência",IF(I30="","Faltam as notas de P e I",IF(K30="","Escolha a resposta",IF(L30="",IF(K30="Aceitar","Justifique a decisão de aceitar","Escreva a ação"),IF(AND(K30<>"Aceitar",OR(M30="",N30="")),"Falta responsável ou prazo",IF(R30="","Avalie o risco residual",IF(R30>I30,"Residual maior que o inicial","Completo")))))))) | V30: =IF(I30="","",IF(AND(OR(J30="Alto",J30="Crítico"),K30="Aceitar"),"Risco alto aceito: peça a decisão da direção",IF(OR(S30="Alto",S30="Crítico"),"Residual ainda alto: reforce a resposta",IF(OR(H30=5,Q30=5),"Impacto 5: tenha plano de contingência",""))))
B32: Resumo automático
B33: Riscos registrados | G33: =COUNTA(E11:E30) -> 0
B34: Riscos com o registro completo | G34: =COUNTIF(U11:U30,"Completo") -> 0
B35: Riscos aceitos | G35: =COUNTIF(K11:K30,"Aceitar") -> 0
B36: Ações atrasadas | G36: =COUNTIF(T11:T30,"Atrasada") -> 0
B37: Riscos com alerta | G37: =SUMPRODUCT(--(LEN(V11:V30)>0)) -> 0
B38: Aviso | G38: =IF(G33=0,"Registre os riscos",IF(G34<G33,"Há risco com o registro incompleto: veja a coluna Conferência",IF(G36>0,"Há ação atrasada",IF($T$5="","Marque a data da revisão","OK")))) -> Registre os riscos

Sheet Mapa
B1: Mapa de riscos
B2: Número de riscos em cada célula da matriz, antes e depois das respostas. Calculado a partir da aba Riscos.
B4: Processo | C4: =IF(Riscos!K4="","",Riscos!K4) | I4: Data da análise | J4: =IF(Riscos!T4="","",Riscos!T4)
B6: Risco inicial | I6: Risco residual
B7: 5 · Muito alto | C7: =COUNTIFS(Riscos!$G$11:$G$30,1,Riscos!$H$11:$H$30,5) -> 0 | D7: =COUNTIFS(Riscos!$G$11:$G$30,2,Riscos!$H$11:$H$30,5) -> 0 | E7: =COUNTIFS(Riscos!$G$11:$G$30,3,Riscos!$H$11:$H$30,5) -> 0 | F7: =COUNTIFS(Riscos!$G$11:$G$30,4,Riscos!$H$11:$H$30,5) -> 0 | G7: =COUNTIFS(Riscos!$G$11:$G$30,5,Riscos!$H$11:$H$30,5) -> 0 | I7: 5 · Muito alto | J7: =COUNTIFS(Riscos!$P$11:$P$30,1,Riscos!$Q$11:$Q$30,5) -> 0 | K7: =COUNTIFS(Riscos!$P$11:$P$30,2,Riscos!$Q$11:$Q$30,5) -> 0 | L7: =COUNTIFS(Riscos!$P$11:$P$30,3,Riscos!$Q$11:$Q$30,5) -> 0 | M7: =COUNTIFS(Riscos!$P$11:$P$30,4,Riscos!$Q$11:$Q$30,5) -> 0 | N7: =COUNTIFS(Riscos!$P$11:$P$30,5,Riscos!$Q$11:$Q$30,5) -> 0
B8: 4 · Alto | C8: =COUNTIFS(Riscos!$G$11:$G$30,1,Riscos!$H$11:$H$30,4) -> 0 | D8: =COUNTIFS(Riscos!$G$11:$G$30,2,Riscos!$H$11:$H$30,4) -> 0 | E8: =COUNTIFS(Riscos!$G$11:$G$30,3,Riscos!$H$11:$H$30,4) -> 0 | F8: =COUNTIFS(Riscos!$G$11:$G$30,4,Riscos!$H$11:$H$30,4) -> 0 | G8: =COUNTIFS(Riscos!$G$11:$G$30,5,Riscos!$H$11:$H$30,4) -> 0 | I8: 4 · Alto | J8: =COUNTIFS(Riscos!$P$11:$P$30,1,Riscos!$Q$11:$Q$30,4) -> 0 | K8: =COUNTIFS(Riscos!$P$11:$P$30,2,Riscos!$Q$11:$Q$30,4) -> 0 | L8: =COUNTIFS(Riscos!$P$11:$P$30,3,Riscos!$Q$11:$Q$30,4) -> 0 | M8: =COUNTIFS(Riscos!$P$11:$P$30,4,Riscos!$Q$11:$Q$30,4) -> 0 | N8: =COUNTIFS(Riscos!$P$11:$P$30,5,Riscos!$Q$11:$Q$30,4) -> 0
B9: 3 · Médio | C9: =COUNTIFS(Riscos!$G$11:$G$30,1,Riscos!$H$11:$H$30,3) -> 0 | D9: =COUNTIFS(Riscos!$G$11:$G$30,2,Riscos!$H$11:$H$30,3) -> 0 | E9: =COUNTIFS(Riscos!$G$11:$G$30,3,Riscos!$H$11:$H$30,3) -> 0 | F9: =COUNTIFS(Riscos!$G$11:$G$30,4,Riscos!$H$11:$H$30,3) -> 0 | G9: =COUNTIFS(Riscos!$G$11:$G$30,5,Riscos!$H$11:$H$30,3) -> 0 | I9: 3 · Médio | J9: =COUNTIFS(Riscos!$P$11:$P$30,1,Riscos!$Q$11:$Q$30,3) -> 0 | K9: =COUNTIFS(Riscos!$P$11:$P$30,2,Riscos!$Q$11:$Q$30,3) -> 0 | L9: =COUNTIFS(Riscos!$P$11:$P$30,3,Riscos!$Q$11:$Q$30,3) -> 0 | M9: =COUNTIFS(Riscos!$P$11:$P$30,4,Riscos!$Q$11:$Q$30,3) -> 0 | N9: =COUNTIFS(Riscos!$P$11:$P$30,5,Riscos!$Q$11:$Q$30,3) -> 0
B10: 2 · Baixo | C10: =COUNTIFS(Riscos!$G$11:$G$30,1,Riscos!$H$11:$H$30,2) -> 0 | D10: =COUNTIFS(Riscos!$G$11:$G$30,2,Riscos!$H$11:$H$30,2) -> 0 | E10: =COUNTIFS(Riscos!$G$11:$G$30,3,Riscos!$H$11:$H$30,2) -> 0 | F10: =COUNTIFS(Riscos!$G$11:$G$30,4,Riscos!$H$11:$H$30,2) -> 0 | G10: =COUNTIFS(Riscos!$G$11:$G$30,5,Riscos!$H$11:$H$30,2) -> 0 | I10: 2 · Baixo | J10: =COUNTIFS(Riscos!$P$11:$P$30,1,Riscos!$Q$11:$Q$30,2) -> 0 | K10: =COUNTIFS(Riscos!$P$11:$P$30,2,Riscos!$Q$11:$Q$30,2) -> 0 | L10: =COUNTIFS(Riscos!$P$11:$P$30,3,Riscos!$Q$11:$Q$30,2) -> 0 | M10: =COUNTIFS(Riscos!$P$11:$P$30,4,Riscos!$Q$11:$Q$30,2) -> 0 | N10: =COUNTIFS(Riscos!$P$11:$P$30,5,Riscos!$Q$11:$Q$30,2) -> 0
B11: 1 · Muito baixo | C11: =COUNTIFS(Riscos!$G$11:$G$30,1,Riscos!$H$11:$H$30,1) -> 0 | D11: =COUNTIFS(Riscos!$G$11:$G$30,2,Riscos!$H$11:$H$30,1) -> 0 | E11: =COUNTIFS(Riscos!$G$11:$G$30,3,Riscos!$H$11:$H$30,1) -> 0 | F11: =COUNTIFS(Riscos!$G$11:$G$30,4,Riscos!$H$11:$H$30,1) -> 0 | G11: =COUNTIFS(Riscos!$G$11:$G$30,5,Riscos!$H$11:$H$30,1) -> 0 | I11: 1 · Muito baixo | J11: =COUNTIFS(Riscos!$P$11:$P$30,1,Riscos!$Q$11:$Q$30,1) -> 0 | K11: =COUNTIFS(Riscos!$P$11:$P$30,2,Riscos!$Q$11:$Q$30,1) -> 0 | L11: =COUNTIFS(Riscos!$P$11:$P$30,3,Riscos!$Q$11:$Q$30,1) -> 0 | M11: =COUNTIFS(Riscos!$P$11:$P$30,4,Riscos!$Q$11:$Q$30,1) -> 0 | N11: =COUNTIFS(Riscos!$P$11:$P$30,5,Riscos!$Q$11:$Q$30,1) -> 0
B12: Impacto ↑ Probabilidade → | C12: 1 · Muito baixa | D12: 2 · Baixa | E12: 3 · Média | F12: 4 · Alta | G12: 5 · Muito alta | I12: Impacto ↑ Probabilidade → | J12: 1 · Muito baixa | K12: 2 · Baixa | L12: 3 · Média | M12: 4 · Alta | N12: 5 · Muito alta
B14: Nível | E14: Inicial | F14: Residual
B15: Baixo | E15: =COUNTIF(Riscos!$J$11:$J$30,"Baixo") -> 0 | F15: =COUNTIF(Riscos!$S$11:$S$30,"Baixo") -> 0
B16: Médio | E16: =COUNTIF(Riscos!$J$11:$J$30,"Médio") -> 0 | F16: =COUNTIF(Riscos!$S$11:$S$30,"Médio") -> 0
B17: Alto | E17: =COUNTIF(Riscos!$J$11:$J$30,"Alto") -> 0 | F17: =COUNTIF(Riscos!$S$11:$S$30,"Alto") -> 0
B18: Crítico | E18: =COUNTIF(Riscos!$J$11:$J$30,"Crítico") -> 0 | F18: =COUNTIF(Riscos!$S$11:$S$30,"Crítico") -> 0
B20: Resumo automático
B21: Riscos avaliados | E21: =COUNT(Riscos!$I$11:$I$30) -> 0
B22: Altos e críticos, inicial | E22: =E17+E18 -> 0
B23: Altos e críticos, residual | E23: =F17+F18 -> 0
B24: Média dos pontos, inicial | E24: =IF(COUNT(Riscos!$I$11:$I$30)=0,"",AVERAGE(Riscos!$I$11:$I$30))
B25: Média dos pontos, residual | E25: =IF(COUNT(Riscos!$R$11:$R$30)=0,"",AVERAGE(Riscos!$R$11:$R$30))
B26: Aviso | E26: =IF(E21=0,"Registre os riscos na aba Riscos",IF(COUNT(Riscos!$R$11:$R$30)<E21,"Há risco sem avaliação residual",IF(E23>0,"Há risco residual alto ou crítico: reforce a resposta","OK"))) -> Registre os riscos na aba Riscos

Sheet Oportunidades
B1: Oportunidades
B2: Uma oportunidade por linha. A conta é a mesma do risco, com o benefício no lugar do impacto.
B4: # | C4: Oportunidade | D4: Processo | E4: Probabilidade | F4: Benefício | G4: Pontos | H4: Prioridade | I4: Decisão | J4: Ação | K4: Responsável | L4: Prazo | M4: Status | N4: Situação
C5: O que pode acontecer de bom | D5: Onde | E5: 1 a 5 | F5: 1 a 5 | G5: Calculado | H5: Faixa | I5: Escolha na lista | J5: Verbo no infinitivo | K5: Cargo ou nome | L5: Data | M5: Da ação | N5: Calculada
B6: Ex. | C6: Cliente atual pede embalagem com material reciclado | D6: Desenvolvimento | E6: 4 | F6: 4 | G6: 16 | H6: Alta | I6: Aproveitar | J6: Abrir projeto de desenvolvimento da nova linha. | K6: Gerente de engenharia | L6: 46356 | M6: Em andamento | N6: No prazo
B7: 1 | G7: =IF(OR(E7="",F7=""),"",E7*F7) | H7: =IF(G7="","",IF(G7>=10,"Alta",IF(G7>=5,"Média","Baixa"))) | N7: =IF(OR(C7="",I7=""),"",IF(I7="Não agir agora","Sem ação",IF(M7="Concluída","Concluída",IF(L7="","Sem prazo",IF(L7<TODAY(),"Atrasada","No prazo")))))
B8: 2 | G8: =IF(OR(E8="",F8=""),"",E8*F8) | H8: =IF(G8="","",IF(G8>=10,"Alta",IF(G8>=5,"Média","Baixa"))) | N8: =IF(OR(C8="",I8=""),"",IF(I8="Não agir agora","Sem ação",IF(M8="Concluída","Concluída",IF(L8="","Sem prazo",IF(L8<TODAY(),"Atrasada","No prazo")))))
B9: 3 | G9: =IF(OR(E9="",F9=""),"",E9*F9) | H9: =IF(G9="","",IF(G9>=10,"Alta",IF(G9>=5,"Média","Baixa"))) | N9: =IF(OR(C9="",I9=""),"",IF(I9="Não agir agora","Sem ação",IF(M9="Concluída","Concluída",IF(L9="","Sem prazo",IF(L9<TODAY(),"Atrasada","No prazo")))))
B10: 4 | G10: =IF(OR(E10="",F10=""),"",E10*F10) | H10: =IF(G10="","",IF(G10>=10,"Alta",IF(G10>=5,"Média","Baixa"))) | N10: =IF(OR(C10="",I10=""),"",IF(I10="Não agir agora","Sem ação",IF(M10="Concluída","Concluída",IF(L10="","Sem prazo",IF(L10<TODAY(),"Atrasada","No prazo")))))
B11: 5 | G11: =IF(OR(E11="",F11=""),"",E11*F11) | H11: =IF(G11="","",IF(G11>=10,"Alta",IF(G11>=5,"Média","Baixa"))) | N11: =IF(OR(C11="",I11=""),"",IF(I11="Não agir agora","Sem ação",IF(M11="Concluída","Concluída",IF(L11="","Sem prazo",IF(L11<TODAY(),"Atrasada","No prazo")))))
B12: 6 | G12: =IF(OR(E12="",F12=""),"",E12*F12) | H12: =IF(G12="","",IF(G12>=10,"Alta",IF(G12>=5,"Média","Baixa"))) | N12: =IF(OR(C12="",I12=""),"",IF(I12="Não agir agora","Sem ação",IF(M12="Concluída","Concluída",IF(L12="","Sem prazo",IF(L12<TODAY(),"Atrasada","No prazo")))))
B13: 7 | G13: =IF(OR(E13="",F13=""),"",E13*F13) | H13: =IF(G13="","",IF(G13>=10,"Alta",IF(G13>=5,"Média","Baixa"))) | N13: =IF(OR(C13="",I13=""),"",IF(I13="Não agir agora","Sem ação",IF(M13="Concluída","Concluída",IF(L13="","Sem prazo",IF(L13<TODAY(),"Atrasada","No prazo")))))
B14: 8 | G14: =IF(OR(E14="",F14=""),"",E14*F14) | H14: =IF(G14="","",IF(G14>=10,"Alta",IF(G14>=5,"Média","Baixa"))) | N14: =IF(OR(C14="",I14=""),"",IF(I14="Não agir agora","Sem ação",IF(M14="Concluída","Concluída",IF(L14="","Sem prazo",IF(L14<TODAY(),"Atrasada","No prazo")))))
B15: 9 | G15: =IF(OR(E15="",F15=""),"",E15*F15) | H15: =IF(G15="","",IF(G15>=10,"Alta",IF(G15>=5,"Média","Baixa"))) | N15: =IF(OR(C15="",I15=""),"",IF(I15="Não agir agora","Sem ação",IF(M15="Concluída","Concluída",IF(L15="","Sem prazo",IF(L15<TODAY(),"Atrasada","No prazo")))))
B16: 10 | G16: =IF(OR(E16="",F16=""),"",E16*F16) | H16: =IF(G16="","",IF(G16>=10,"Alta",IF(G16>=5,"Média","Baixa"))) | N16: =IF(OR(C16="",I16=""),"",IF(I16="Não agir agora","Sem ação",IF(M16="Concluída","Concluída",IF(L16="","Sem prazo",IF(L16<TODAY(),"Atrasada","No prazo")))))
B18: Resumo automático
B19: Oportunidades registradas | E19: =COUNTA(C7:C16) -> 0
B20: Prioridade alta | E20: =COUNTIF(H7:H16,"Alta") -> 0
B21: Com decisão de aproveitar ou testar | E21: =COUNTIF(I7:I16,"Aproveitar")+COUNTIF(I7:I16,"Testar") -> 0
B22: Ações atrasadas | E22: =COUNTIF(N7:N16,"Atrasada") -> 0
B23: Aviso | E23: =IF(E19=0,"Registre as oportunidades",IF(COUNT(G7:G16)<E19,"Há oportunidade sem as duas notas",IF(COUNTA(I7:I16)<E19,"Há oportunidade sem decisão",IF(SUMPRODUCT((H7:H16="Alta")*(I7:I16="Não agir agora"))>0,"Há oportunidade de prioridade alta sem ação",IF(E22>0,"Há ação atrasada","OK"))))) -> Registre as oportunidades

Sheet Escalas
B1: Escalas, níveis e respostas
B2: Referência para as notas. Ajuste as descrições à sua organização e use as mesmas em todos os processos.
B4: Probabilidade e impacto
B5: Nota | C5: Probabilidade | D5: O evento acontece | E5: Impacto | F5: Se acontecer
B6: 1 | C6: Muito baixa | D6: Menos de uma vez a cada cinco anos. | E6: Muito baixo | F6: Resolvido na rotina, sem efeito no resultado.
B7: 2 | C7: Baixa | D7: Uma vez em um período de um a cinco anos. | E7: Baixo | F7: Retrabalho interno ou custo pequeno. O cliente não percebe.
B8: 3 | C8: Média | D8: Cerca de uma vez por ano. | E8: Médio | F8: Atraso ou falha percebida pelo cliente. Reclamação.
B9: 4 | C9: Alta | D9: Algumas vezes por ano. | E9: Alto | F9: Vários clientes afetados, perda de cliente ou custo alto.
B10: 5 | C10: Muito alta | D10: Uma vez por mês, ou mais. | E10: Muito alto | F10: Dano a pessoas, descumprimento da lei ou parada da operação.
B12: Benefício, para as oportunidades
B13: 1 | C13: Muito baixo | D13: Ganho pequeno, difícil de perceber.
B14: 2 | C14: Baixo | D14: Ganho interno, sem efeito para o cliente.
B15: 3 | C15: Médio | D15: Ganho percebido pelo cliente ou economia relevante.
B16: 4 | C16: Alto | D16: Novo cliente, nova linha ou redução grande de custo.
B17: 5 | C17: Muito alto | D17: Muda a posição da organização no mercado.
B19: Níveis e conduta
C20: Baixo | D20: De 1 a 4 pontos | E20: Aceitar e acompanhar na revisão anual.
C21: Médio | D21: De 5 a 9 pontos | E21: Tratar quando o custo compensar. Revisar a cada seis meses.
C22: Alto | D22: De 10 a 16 pontos | E22: Tratar, com ação, responsável e prazo.
C23: Crítico | D23: De 20 a 25 pontos | E23: Tratar de imediato, com decisão da direção.
B25: Respostas ao risco
C26: Resposta | D26: O que é | E26: Efeito no risco | F26: Exemplo
B27: 1 | C27: Evitar | D27: Deixar de fazer a atividade que gera o risco, ou impedir que ela aconteça. | E27: A probabilidade cai para o mínimo. | F27: Bloquear no sistema a compra de fornecedor não homologado.
B28: 2 | C28: Reduzir | D28: Agir sobre a causa, para o evento ficar menos provável, ou sobre a consequência, para o efeito ficar menor. | E28: A probabilidade ou o impacto diminuem. | F28: Homologar um segundo fornecedor. Manter estoque mínimo.
B29: 3 | C29: Compartilhar | D29: Dividir o efeito com outra parte, por contrato ou seguro. | E29: O impacto para a organização diminui. | F29: Contratar seguro. Fixar o preço em contrato.
B30: 4 | C30: Aceitar | D30: Decidir, com consciência, não agir agora, e acompanhar o risco. | E30: O nível não muda. | F30: Acompanhar o prazo da transportadora pelo indicador.

Sheet Checklist
B1: Checklist de validação da matriz
B2: Escolha o status de cada item na lista suspensa (coluna em amarelo-claro).
B4: # | C4: Item de verificação | D4: Status | E4: Observações
B5: 1 | C5: O escopo da análise está definido: processo, objetivo e período.
B6: 2 | C6: As escalas de probabilidade e de impacto estão escritas e foram entendidas pelo grupo.
B7: 3 | C7: Os riscos foram levantados com quem executa o processo.
B8: 4 | C8: Cada risco está descrito com causa, evento e consequência.
B9: 5 | C9: Os problemas que já aconteceram foram separados e tratados como não conformidades.
B10: 6 | C10: As oportunidades também foram levantadas.
B11: 7 | C11: A probabilidade e o impacto de cada risco têm justificativa.
B12: 8 | C12: Os riscos de impacto máximo têm plano de contingência.
B13: 9 | C13: Cada risco alto ou crítico tem resposta, responsável e prazo.
B14: 10 | C14: O risco residual foi avaliado depois das ações.
B15: 11 | C15: A eficácia das ações foi verificada.
B16: 12 | C16: A matriz tem data de revisão definida.
B18: Resumo automático
B19: Itens atendidos (Sim) | D19: =COUNTIF(D5:D16,"Sim") -> 0
B20: Itens parciais | D20: =COUNTIF(D5:D16,"Parcial") -> 0
B21: Itens não atendidos | D21: =COUNTIF(D5:D16,"Não") -> 0
B22: Itens sem resposta | D22: =COUNTBLANK(D5:D16) -> 12
B23: Percentual atendido | D23: =D19/ROWS(D5:D16) -> 0
B24: Situação | D24: =IF(D19=ROWS(D5:D16),"Validado",IF(D22>0,"Em andamento","Com pendências")) -> Em andamento

Sheet Exemplo 1 - Pizzaria
B1: Matriz de riscos
B2: Exemplo preenchido, para consulta. Use as abas Riscos, Mapa e Oportunidades para a sua matriz.
B4: Organização | D4: Pizzaria (loja com salão e delivery)
B5: Processo | D5: Atender pedido de delivery
B6: Objetivo do processo | D6: Entregar 95% dos pedidos em até 40 minutos, sem falhas de segurança do alimento.
B7: Origem dos riscos | D7: Ameaças da Matriz SWOT e lacuna do requisito 6.1 no diagnóstico de 02/10/2026.
B8: Data e participantes | D8: 05/10/2026. Gerente da loja, com a equipe dos dois turnos.
B9: Data da revisão | D9: 46482
B11: Identificação | G11: Análise | K11: Resposta | O11: Risco residual
B12: Nº | C12: Processo ou etapa | D12: Causa | E12: Evento | F12: Consequência | G12: P | H12: I | I12: Pontos | J12: Nível | K12: Resposta | L12: Ação ou justificativa | M12: Responsável | N12: Prazo | O12: P | P12: I | Q12: Pontos | R12: Nível
B13: R1 | C13: Expedição | D13: Chuva forte nas noites de pico | E13: Faltam entregadores | F13: Entregas fora do prazo e reclamações | G13: 4 | H13: 3 | I13: =G13*H13 -> 12 | J13: =IF(I13="","",IF(I13>=20,"Crítico",IF(I13>=10,"Alto",IF(I13>=5,"Médio","Baixo")))) -> Alto | K13: Reduzir | L13: Manter dois entregadores de sobreaviso nos dias com previsão de chuva. | M13: Líder da expedição | N13: 46325 | O13: 2 | P13: 3 | Q13: =O13*P13 -> 6 | R13: =IF(Q13="","",IF(Q13>=20,"Crítico",IF(Q13>=10,"Alto",IF(Q13>=5,"Médio","Baixo")))) -> Médio
B14: R2 | C14: Registro do pedido | D14: Queda da internet ou do sistema | E14: A loja fica sem registrar pedidos | F14: Pedidos perdidos e clientes sem resposta | G14: 3 | H14: 4 | I14: =G14*H14 -> 12 | J14: =IF(I14="","",IF(I14>=20,"Crítico",IF(I14>=10,"Alto",IF(I14>=5,"Médio","Baixo")))) -> Alto | K14: Reduzir | L14: Ter um celular com internet móvel e um bloco de pedidos em papel para a contingência. | M14: Atendente líder | N14: 46318 | O14: 3 | P14: 2 | Q14: =O14*P14 -> 6 | R14: =IF(Q14="","",IF(Q14>=20,"Crítico",IF(Q14>=10,"Alto",IF(Q14>=5,"Médio","Baixo")))) -> Médio
B15: R3 | C15: Armazenamento | D15: Falha do compressor da câmara fria | E15: A temperatura sobe sem ninguém perceber | F15: Perda de insumos e risco para a saúde do cliente | G15: 2 | H15: 5 | I15: =G15*H15 -> 10 | J15: =IF(I15="","",IF(I15>=20,"Crítico",IF(I15>=10,"Alto",IF(I15>=5,"Médio","Baixo")))) -> Alto | K15: Reduzir | L15: Fazer a manutenção preventiva a cada seis meses e instalar alarme de temperatura. | M15: Pizzaiolo líder | N15: 46339 | O15: 1 | P15: 5 | Q15: =O15*P15 -> 5 | R15: =IF(Q15="","",IF(Q15>=20,"Crítico",IF(Q15>=10,"Alto",IF(Q15>=5,"Médio","Baixo")))) -> Médio
B16: R4 | C16: Compras | D16: Um só fornecedor de queijo | E16: O fornecedor atrasa a entrega | F16: Sabores fora do cardápio no fim de semana | G16: 3 | H16: 3 | I16: =G16*H16 -> 9 | J16: =IF(I16="","",IF(I16>=20,"Crítico",IF(I16>=10,"Alto",IF(I16>=5,"Médio","Baixo")))) -> Médio | K16: Reduzir | L16: Homologar um segundo fornecedor de queijo. | M16: Gerente da loja | N16: 46353 | O16: 2 | P16: 2 | Q16: =O16*P16 -> 4 | R16: =IF(Q16="","",IF(Q16>=20,"Crítico",IF(Q16>=10,"Alto",IF(Q16>=5,"Médio","Baixo")))) -> Baixo
B17: R5 | C17: Expedição | D17: Pressa e moto sem revisão | E17: Acidente com o entregador | F17: Dano à pessoa e entregas interrompidas | G17: 2 | H17: 5 | I17: =G17*H17 -> 10 | J17: =IF(I17="","",IF(I17>=20,"Crítico",IF(I17>=10,"Alto",IF(I17>=5,"Médio","Baixo")))) -> Alto | K17: Compartilhar | L17: Revisar as motos todo mês, treinar direção segura e contratar seguro. | M17: Líder da expedição | N17: 46339 | O17: 1 | P17: 5 | Q17: =O17*P17 -> 5 | R17: =IF(Q17="","",IF(Q17>=20,"Crítico",IF(Q17>=10,"Alto",IF(Q17>=5,"Médio","Baixo")))) -> Médio
B18: R6 | C18: Produção | D18: Só o pizzaiolo líder sabe regular o forno | E18: O pizzaiolo líder sai ou se afasta | F18: Pizzas fora do padrão e atraso na produção | G18: 2 | H18: 4 | I18: =G18*H18 -> 8 | J18: =IF(I18="","",IF(I18>=20,"Crítico",IF(I18>=10,"Alto",IF(I18>=5,"Médio","Baixo")))) -> Médio | K18: Reduzir | L18: Registrar a regulagem do forno e treinar um segundo pizzaiolo. | M18: Pizzaiolo líder | N18: 46353 | O18: 2 | P18: 2 | Q18: =O18*P18 -> 4 | R18: =IF(Q18="","",IF(Q18>=20,"Crítico",IF(Q18>=10,"Alto",IF(Q18>=5,"Médio","Baixo")))) -> Baixo
B19: R7 | C19: Compras | D19: Alta no preço dos insumos | E19: O custo da pizza sobe | F19: Margem menor ou aumento de preço ao cliente | G19: 4 | H19: 2 | I19: =G19*H19 -> 8 | J19: =IF(I19="","",IF(I19>=20,"Crítico",IF(I19>=10,"Alto",IF(I19>=5,"Médio","Baixo")))) -> Médio | K19: Aceitar | L19: O preço dos insumos não depende da loja. O gerente acompanha os preços todo mês. | M19: Gerente da loja | N19: Sem ação | O19: 4 | P19: 2 | Q19: =O19*P19 -> 8 | R19: =IF(Q19="","",IF(Q19>=20,"Crítico",IF(Q19>=10,"Alto",IF(Q19>=5,"Médio","Baixo")))) -> Médio
B20: R8 | C20: Produção | D20: Sabor novo com ingrediente alergênico | E20: O cardápio não avisa o cliente | F20: Reação alérgica e responsabilidade legal | G20: 2 | H20: 5 | I20: =G20*H20 -> 10 | J20: =IF(I20="","",IF(I20>=20,"Crítico",IF(I20>=10,"Alto",IF(I20>=5,"Médio","Baixo")))) -> Alto | K20: Evitar | L20: Só cadastrar sabor novo no sistema com a ficha de alergênicos preenchida. | M20: Gerente da loja | N20: 46311 | O20: 1 | P20: 5 | Q20: =O20*P20 -> 5 | R20: =IF(Q20="","",IF(Q20>=20,"Crítico",IF(Q20>=10,"Alto",IF(Q20>=5,"Médio","Baixo")))) -> Médio
B22: Riscos por nível
B23: Nível | E23: Inicial | F23: Residual
B24: Baixo | E24: =COUNTIF($J$13:$J$20,"Baixo") -> 0 | F24: =COUNTIF($R$13:$R$20,"Baixo") -> 2
B25: Médio | E25: =COUNTIF($J$13:$J$20,"Médio") -> 3 | F25: =COUNTIF($R$13:$R$20,"Médio") -> 6
B26: Alto | E26: =COUNTIF($J$13:$J$20,"Alto") -> 5 | F26: =COUNTIF($R$13:$R$20,"Alto") -> 0
B27: Crítico | E27: =COUNTIF($J$13:$J$20,"Crítico") -> 0 | F27: =COUNTIF($R$13:$R$20,"Crítico") -> 0
B29: Resumo automático
B30: Riscos avaliados | E30: =COUNT(I13:I20) -> 8
B31: Altos e críticos, inicial | E31: =E26+E27 -> 5
B32: Altos e críticos, residual | E32: =F26+F27 -> 0
B33: Média dos pontos, inicial | E33: =AVERAGE(I13:I20) -> 9.875
B34: Média dos pontos, residual | E34: =AVERAGE(Q13:Q20) -> 5.375
B35: Riscos de impacto 5 | E35: =COUNTIF(H13:H20,5) -> 3
B36: Riscos aceitos | E36: =COUNTIF(K13:K20,"Aceitar") -> 1

Sheet Exemplo 2 - Compras
B1: Matriz de riscos
B2: Exemplo preenchido, para consulta. Use as abas Riscos, Mapa e Oportunidades para a sua matriz.
B4: Organização | D4: Indústria de embalagens plásticas
B5: Processo | D5: Adquirir materiais e serviços
B6: Objetivo do processo | D6: Fornecer os materiais certos, no prazo, sem parar a produção.
B7: Origem dos riscos | D7: Diagnóstico de 25/09/2026, auditoria 2026-07 e RNC 2026-31.
B8: Data e participantes | D8: 12/10/2026. Gerente de Suprimentos, com compradores, Recebimento e Qualidade.
B9: Data da revisão | D9: 46489
B11: Identificação | G11: Análise | K11: Resposta | O11: Risco residual
B12: Nº | C12: Processo ou etapa | D12: Causa | E12: Evento | F12: Consequência | G12: P | H12: I | I12: Pontos | J12: Nível | K12: Resposta | L12: Ação ou justificativa | M12: Responsável | N12: Prazo | O12: P | P12: I | Q12: Pontos | R12: Nível
B13: C1 | C13: Planejamento de compras | D13: Um só fornecedor de resina | E13: O fornecedor deixa de entregar | F13: Parada da produção por falta de material | G13: 4 | H13: 5 | I13: =G13*H13 -> 20 | J13: =IF(I13="","",IF(I13>=20,"Crítico",IF(I13>=10,"Alto",IF(I13>=5,"Médio","Baixo")))) -> Crítico | K13: Reduzir | L13: Homologar um segundo fornecedor de resina e manter estoque mínimo de 15 dias. | M13: Gerente de Suprimentos | N13: 46374 | O13: 2 | P13: 3 | Q13: =O13*P13 -> 6 | R13: =IF(Q13="","",IF(Q13>=20,"Crítico",IF(Q13>=10,"Alto",IF(Q13>=5,"Médio","Baixo")))) -> Médio
B14: C2 | C14: Requisição | D14: Requisição sem especificação técnica | E14: O item comprado é diferente do necessário | F14: Devolução ao fornecedor e atraso de 9 dias | G14: 4 | H14: 3 | I14: =G14*H14 -> 12 | J14: =IF(I14="","",IF(I14>=20,"Crítico",IF(I14>=10,"Alto",IF(I14>=5,"Médio","Baixo")))) -> Alto | K14: Reduzir | L14: Ações do RNC 2026-31: campo obrigatório, cadastro dos itens e revisão do procedimento. | M14: Gerente de Suprimentos | N14: 46318 | O14: 2 | P14: 3 | Q14: =O14*P14 -> 6 | R14: =IF(Q14="","",IF(Q14>=20,"Crítico",IF(Q14>=10,"Alto",IF(Q14>=5,"Médio","Baixo")))) -> Médio
B15: C3 | C15: Avaliação de fornecedores | D15: Fornecedor crítico sem avaliação de desempenho | E15: A qualidade do fornecedor cai sem ser percebida | F15: Material não conforme na produção | G15: 3 | H15: 4 | I15: =G15*H15 -> 12 | J15: =IF(I15="","",IF(I15>=20,"Crítico",IF(I15>=10,"Alto",IF(I15>=5,"Médio","Baixo")))) -> Alto | K15: Reduzir | L15: Avaliar os 12 fornecedores críticos a cada semestre, com registro. | M15: Comprador sênior | N15: 46325 | O15: 2 | P15: 4 | Q15: =O15*P15 -> 8 | R15: =IF(Q15="","",IF(Q15>=20,"Crítico",IF(Q15>=10,"Alto",IF(Q15>=5,"Médio","Baixo")))) -> Médio
B16: C4 | C16: Negociação | D16: Resina com preço ligado ao dólar | E16: O câmbio sobe depois do pedido | F16: Custo acima do orçamento | G16: 4 | H16: 3 | I16: =G16*H16 -> 12 | J16: =IF(I16="","",IF(I16>=20,"Crítico",IF(I16>=10,"Alto",IF(I16>=5,"Médio","Baixo")))) -> Alto | K16: Compartilhar | L16: Negociar contrato com preço fixo por seis meses. | M16: Gerente de Suprimentos | N16: 46353 | O16: 4 | P16: 2 | Q16: =O16*P16 -> 8 | R16: =IF(Q16="","",IF(Q16>=20,"Crítico",IF(Q16>=10,"Alto",IF(Q16>=5,"Médio","Baixo")))) -> Médio
B17: C5 | C17: Compra de urgência | D17: Pressão de prazo da produção | E17: Compra de fornecedor não homologado | F17: Material sem garantia de qualidade | G17: 3 | H17: 4 | I17: =G17*H17 -> 12 | J17: =IF(I17="","",IF(I17>=20,"Crítico",IF(I17>=10,"Alto",IF(I17>=5,"Médio","Baixo")))) -> Alto | K17: Evitar | L17: Bloquear no sistema o pedido para fornecedor não homologado. | M17: Analista de sistemas | N17: 46339 | O17: 1 | P17: 4 | Q17: =O17*P17 -> 4 | R17: =IF(Q17="","",IF(Q17>=20,"Crítico",IF(Q17>=10,"Alto",IF(Q17>=5,"Médio","Baixo")))) -> Baixo
B18: C6 | C18: Aprovação | D18: Compra acima da alçada sem conferência | E18: Favorecimento de um fornecedor | F18: Perda financeira e dano à imagem | G18: 1 | H18: 5 | I18: =G18*H18 -> 5 | J18: =IF(I18="","",IF(I18>=20,"Crítico",IF(I18>=10,"Alto",IF(I18>=5,"Médio","Baixo")))) -> Médio | K18: Aceitar | L18: As três cotações e as alçadas já reduzem a probabilidade ao mínimo. A auditoria confere o controle. | M18: Gerente de Suprimentos | N18: Sem ação | O18: 1 | P18: 5 | Q18: =O18*P18 -> 5 | R18: =IF(Q18="","",IF(Q18>=20,"Crítico",IF(Q18>=10,"Alto",IF(Q18>=5,"Médio","Baixo")))) -> Médio
B19: C7 | C19: Recebimento | D19: Transportadora com frota reduzida | E19: O material chega depois do prazo | F19: Reprogramação da produção | G19: 4 | H19: 2 | I19: =G19*H19 -> 8 | J19: =IF(I19="","",IF(I19>=20,"Crítico",IF(I19>=10,"Alto",IF(I19>=5,"Médio","Baixo")))) -> Médio | K19: Aceitar | L19: O efeito é pequeno, e o indicador de prazo do Recebimento acompanha o risco. | M19: Líder do Recebimento | N19: Sem ação | O19: 4 | P19: 2 | Q19: =O19*P19 -> 8 | R19: =IF(Q19="","",IF(Q19>=20,"Crítico",IF(Q19>=10,"Alto",IF(Q19>=5,"Médio","Baixo")))) -> Médio
B20: C8 | C20: Homologação | D20: Fornecedor sem licença ambiental | E20: O fornecedor é autuado ou interditado | F20: Falta de material e dano à imagem | G20: 2 | H20: 4 | I20: =G20*H20 -> 8 | J20: =IF(I20="","",IF(I20>=20,"Crítico",IF(I20>=10,"Alto",IF(I20>=5,"Médio","Baixo")))) -> Médio | K20: Reduzir | L20: Exigir os documentos legais na homologação e a cada renovação. | M20: Comprador sênior | N20: 46353 | O20: 1 | P20: 4 | Q20: =O20*P20 -> 4 | R20: =IF(Q20="","",IF(Q20>=20,"Crítico",IF(Q20>=10,"Alto",IF(Q20>=5,"Médio","Baixo")))) -> Baixo
B22: Riscos por nível
B23: Nível | E23: Inicial | F23: Residual
B24: Baixo | E24: =COUNTIF($J$13:$J$20,"Baixo") -> 0 | F24: =COUNTIF($R$13:$R$20,"Baixo") -> 2
B25: Médio | E25: =COUNTIF($J$13:$J$20,"Médio") -> 3 | F25: =COUNTIF($R$13:$R$20,"Médio") -> 6
B26: Alto | E26: =COUNTIF($J$13:$J$20,"Alto") -> 4 | F26: =COUNTIF($R$13:$R$20,"Alto") -> 0
B27: Crítico | E27: =COUNTIF($J$13:$J$20,"Crítico") -> 1 | F27: =COUNTIF($R$13:$R$20,"Crítico") -> 0
B29: Resumo automático
B30: Riscos avaliados | E30: =COUNT(I13:I20) -> 8
B31: Altos e críticos, inicial | E31: =E26+E27 -> 5
B32: Altos e críticos, residual | E32: =F26+F27 -> 0
B33: Média dos pontos, inicial | E33: =AVERAGE(I13:I20) -> 11.125
B34: Média dos pontos, residual | E34: =AVERAGE(Q13:Q20) -> 6.125
B35: Riscos de impacto 5 | E35: =COUNTIF(H13:H20,5) -> 2
B36: Riscos aceitos | E36: =COUNTIF(K13:K20,"Aceitar") -> 2
